{
    "total": [
        {
            "id": "100088895482183",
            "count": 0
        },
        {
            "id": "61565153272718",
            "count": 0
        },
        {
            "id": "100076245554321",
            "count": 38
        },
        {
            "id": "61561853472054",
            "count": 0
        },
        {
            "id": "61574672918152",
            "count": 23
        },
        {
            "id": "61574979014503",
            "count": 0
        },
        {
            "id": "61576076879509",
            "count": 0
        },
        {
            "id": "61577013303867",
            "count": 0
        },
        {
            "id": "100094196739170",
            "count": 12
        },
        {
            "id": "61577076481950",
            "count": 16
        }
    ],
    "week": [
        {
            "id": "100088895482183",
            "count": 0
        },
        {
            "id": "61565153272718",
            "count": 0
        },
        {
            "id": "100076245554321",
            "count": 38
        },
        {
            "id": "61561853472054",
            "count": 0
        },
        {
            "id": "61574672918152",
            "count": 23
        },
        {
            "id": "61574979014503",
            "count": 0
        },
        {
            "id": "61576076879509",
            "count": 0
        },
        {
            "id": "61577013303867",
            "count": 0
        },
        {
            "id": "100094196739170",
            "count": 12
        },
        {
            "id": "61577076481950",
            "count": 16
        }
    ],
    "day": [
        {
            "id": "100088895482183",
            "count": 0
        },
        {
            "id": "61565153272718",
            "count": 0
        },
        {
            "id": "100076245554321",
            "count": 38
        },
        {
            "id": "61561853472054",
            "count": 0
        },
        {
            "id": "61574672918152",
            "count": 23
        },
        {
            "id": "61574979014503",
            "count": 0
        },
        {
            "id": "61576076879509",
            "count": 0
        },
        {
            "id": "61577013303867",
            "count": 0
        },
        {
            "id": "100094196739170",
            "count": 12
        },
        {
            "id": "61577076481950",
            "count": 16
        }
    ],
    "time": 1,
    "last": {
        "time": 5,
        "day": [
            {
                "id": "100088895482183",
                "count": 0
            },
            {
                "id": "61565153272718",
                "count": 0
            },
            {
                "id": "100076245554321",
                "count": 0
            },
            {
                "id": "61561853472054",
                "count": 0
            },
            {
                "id": "61574672918152",
                "count": 0
            },
            {
                "id": "61574979014503",
                "count": 0
            },
            {
                "id": "100094196739170",
                "count": 0
            },
            {
                "id": "100081276783877",
                "count": 0
            },
            {
                "id": "61576076879509",
                "count": 0
            },
            {
                "id": "61577013303867",
                "count": 0
            },
            {
                "id": "61577076481950",
                "count": 0
            }
        ],
        "week": [
            {
                "id": "100088895482183",
                "count": 0
            },
            {
                "id": "61565153272718",
                "count": 0
            },
            {
                "id": "100076245554321",
                "count": 0
            },
            {
                "id": "61561853472054",
                "count": 0
            },
            {
                "id": "61574672918152",
                "count": 0
            },
            {
                "id": "61574979014503",
                "count": 0
            },
            {
                "id": "100094196739170",
                "count": 0
            },
            {
                "id": "100081276783877",
                "count": 0
            },
            {
                "id": "61576076879509",
                "count": 0
            },
            {
                "id": "61577013303867",
                "count": 0
            },
            {
                "id": "61577076481950",
                "count": 0
            }
        ]
    },
    "lastInteraction": {
        "100076245554321": 1749214184227,
        "61574672918152": 1749214538000,
        "61577076481950": 1749213001485,
        "100094196739170": 1749212033298
    }
}